{
  "__inputs": [
    {
      "name": "prometheus",
      "label": "prometheus",
      "description": "",
      "type": "datasource",
      "pluginId": "prometheus",
      "pluginName": "Prometheus"
    }
  ],
  "__requires": [
    {
      "type": "grafana",
      "id": "grafana",
      "name": "Grafana",
      "version": "5.1.1"
    },
    {
      "type": "panel",
      "id": "graph",
      "name": "Graph",
      "version": "5.0.0"
    },
    {
      "type": "datasource",
      "id": "prometheus",
      "name": "prometheus",
      "version": "5.0.0"
    },
    {
      "type": "panel",
      "id": "singlestat",
      "name": "Singlestat",
      "version": "5.0.0"
    }
  ],
  "annotations": {
    "list": [
      {
        "builtIn": 1,
        "datasource": "-- Grafana --",
        "enable": true,
        "hide": true,
        "iconColor": "rgba(0, 211, 255, 1)",
        "name": "Annotations & Alerts",
        "type": "dashboard"
      }
    ]
  },
  "editable": true,
  "gnetId": null,
  "graphTooltip": 0,
  "id": null,
  "links": [],
  "panels": [
    {
      "cacheTimeout": null,
      "colorBackground": false,
      "colorValue": false,
      "colors": [
        "#299c46",
        "rgba(237, 129, 40, 0.89)",
        "#d44a3a"
      ],
      "datasource": "prometheus",
      "format": "none",
      "gauge": {
        "maxValue": 100,
        "minValue": 0,
        "show": false,
        "thresholdLabels": false,
        "thresholdMarkers": true
      },
      "gridPos": {
        "h": 5,
        "w": 3,
        "x": 0,
        "y": 0
      },
      "id": 2,
      "interval": null,
      "links": [],
      "mappingType": 1,
      "mappingTypes": [
        {
          "name": "value to text",
          "value": 1
        },
        {
          "name": "range to text",
          "value": 2
        }
      ],
      "maxDataPoints": 100,
      "nullPointMode": "connected",
      "nullText": null,
      "postfix": "",
      "postfixFontSize": "50%",
      "prefix": "",
      "prefixFontSize": "50%",
      "rangeMaps": [
        {
          "from": "null",
          "text": "N/A",
          "to": "null"
        }
      ],
      "sparkline": {
        "fillColor": "rgba(31, 118, 189, 0.18)",
        "full": false,
        "lineColor": "rgb(31, 120, 193)",
        "show": false
      },
      "tableColumn": "__name__",
      "targets": [
        {
          "expr": "live_buckets",
          "format": "time_series",
          "hide": false,
          "instant": false,
          "interval": "",
          "intervalFactor": 1,
          "refId": "A"
        }
      ],
      "thresholds": "",
      "title": "Live Buckets",
      "type": "singlestat",
      "valueFontSize": "80%",
      "valueMaps": [
        {
          "op": "=",
          "text": "N/A",
          "value": "null"
        }
      ],
      "valueName": "current"
    },
    {
      "aliasColors": {},
      "bars": false,
      "dashLength": 10,
      "dashes": false,
      "datasource": "prometheus",
      "fill": 1,
      "gridPos": {
        "h": 10,
        "w": 13,
        "x": 3,
        "y": 0
      },
      "id": 5,
      "legend": {
        "avg": false,
        "current": false,
        "max": false,
        "min": false,
        "show": true,
        "total": false,
        "values": false
      },
      "lines": true,
      "linewidth": 1,
      "links": [],
      "nullPointMode": "connected",
      "percentage": false,
      "pointradius": 5,
      "points": false,
      "renderer": "flot",
      "seriesOverrides": [],
      "spaceLength": 10,
      "stack": false,
      "steppedLine": false,
      "targets": [
        {
          "expr": "rate(update_time_sum[5m])/rate(update_time_count[5m])",
          "format": "time_series",
          "hide": false,
          "intervalFactor": 1,
          "legendFormat": "average",
          "refId": "A"
        },
        {
          "expr": "histogram_quantile(0.99, sum(rate(update_time_bucket[5m])) by (le))",
          "format": "time_series",
          "intervalFactor": 1,
          "legendFormat": "99th",
          "refId": "B"
        },
        {
          "expr": "histogram_quantile(0.95, sum(rate(update_time_bucket[5m])) by (le))",
          "format": "time_series",
          "intervalFactor": 1,
          "legendFormat": "95th",
          "refId": "C"
        },
        {
          "expr": "histogram_quantile(0.75, sum(rate(update_time_bucket[5m])) by (le))",
          "format": "time_series",
          "intervalFactor": 1,
          "legendFormat": "75th",
          "refId": "D"
        },
        {
          "expr": "histogram_quantile(0.50, sum(rate(update_time_bucket[5m])) by (le))",
          "format": "time_series",
          "intervalFactor": 1,
          "legendFormat": "50th",
          "refId": "E"
        }
      ],
      "thresholds": [],
      "timeFrom": null,
      "timeShift": null,
      "title": "Update Request Duration",
      "tooltip": {
        "shared": true,
        "sort": 0,
        "value_type": "individual"
      },
      "type": "graph",
      "xaxis": {
        "buckets": null,
        "mode": "time",
        "name": null,
        "show": true,
        "values": []
      },
      "yaxes": [
        {
          "format": "s",
          "label": null,
          "logBase": 1,
          "max": null,
          "min": null,
          "show": true
        },
        {
          "format": "short",
          "label": null,
          "logBase": 1,
          "max": null,
          "min": null,
          "show": true
        }
      ],
      "yaxis": {
        "align": false,
        "alignLevel": null
      }
    },
    {
      "cacheTimeout": null,
      "colorBackground": false,
      "colorValue": false,
      "colors": [
        "#299c46",
        "rgba(237, 129, 40, 0.89)",
        "#d44a3a"
      ],
      "datasource": "prometheus",
      "format": "none",
      "gauge": {
        "maxValue": 100,
        "minValue": 0,
        "show": false,
        "thresholdLabels": false,
        "thresholdMarkers": true
      },
      "gridPos": {
        "h": 5,
        "w": 3,
        "x": 0,
        "y": 5
      },
      "id": 3,
      "interval": null,
      "links": [],
      "mappingType": 1,
      "mappingTypes": [
        {
          "name": "value to text",
          "value": 1
        },
        {
          "name": "range to text",
          "value": 2
        }
      ],
      "maxDataPoints": 100,
      "nullPointMode": "connected",
      "nullText": null,
      "postfix": "",
      "postfixFontSize": "50%",
      "prefix": "",
      "prefixFontSize": "50%",
      "rangeMaps": [
        {
          "from": "null",
          "text": "N/A",
          "to": "null"
        }
      ],
      "sparkline": {
        "fillColor": "rgba(31, 118, 189, 0.18)",
        "full": false,
        "lineColor": "rgb(31, 120, 193)",
        "show": false
      },
      "tableColumn": "",
      "targets": [
        {
          "expr": "live_nccos",
          "format": "time_series",
          "hide": false,
          "instant": false,
          "intervalFactor": 1,
          "refId": "A"
        }
      ],
      "thresholds": "",
      "title": "Live NCCOs",
      "type": "singlestat",
      "valueFontSize": "80%",
      "valueMaps": [
        {
          "op": "=",
          "text": "N/A",
          "value": "null"
        }
      ],
      "valueName": "current"
    }
  ],
  "refresh": false,
  "schemaVersion": 16,
  "style": "dark",
  "tags": [],
  "templating": {
    "list": []
  },
  "time": {
    "from": "now-30m",
    "to": "now"
  },
  "timepicker": {
    "refresh_intervals": [
      "5s",
      "10s",
      "30s",
      "1m",
      "5m",
      "15m",
      "30m",
      "1h",
      "2h",
      "1d"
    ],
    "time_options": [
      "5m",
      "15m",
      "1h",
      "6h",
      "12h",
      "24h",
      "2d",
      "7d",
      "30d"
    ]
  },
  "timezone": "",
  "title": "nccostorage",
  "uid": "EGlPJT7iz",
  "version": 2
}
